floggit/__init__.py
floggit/floggit.py
floggit/utils.py
floggit-0.0.19.dist-info/METADATA
floggit-0.0.19.dist-info/WHEEL
floggit-0.0.19.dist-info/top_level.txt
floggit-0.0.19.dist-info/RECORD
