Metadata-Version: 2.1
Name: floggit
Version: 0.0.19
Summary: log function inputs and outputs at runtime
Home-page: https://github.com/dcyd-inc/floggit
Author: dcyd, inc.
Author-email: info@dcyd.io
Classifier: Programming Language :: Python :: 3
Classifier: Operating System :: OS Independent
Requires-Python: >=3.9
Requires-Dist: google-cloud-logging>=3.0.0
Requires-Dist: flask>=3
Requires-Dist: networkx>=3
